pytwoch/__init__.py
pytwoch/api_urls.py
pytwoch/board.py
pytwoch/post.py
pytwoch/thread.py
pytwoch-0.0.5.dist-info/METADATA
pytwoch-0.0.5.dist-info/RECORD
pytwoch-0.0.5.dist-info/WHEEL
pytwoch-0.0.5.dist-info/top_level.txt
