Metadata-Version: 2.1
Name: pytwoch
Version: 0.0.5
Summary: A simple Python wrapper for 2ch.hk API
Home-page: https://github.com/TheUnravelGhoul/py2ch
Author: TheUnravelGhoul
Author-email: densmorgon@gmail.com
License: UNKNOWN
Platform: UNKNOWN
Classifier: Programming Language :: Python :: 3
Classifier: License :: OSI Approved :: MIT License
Classifier: Operating System :: OS Independent
Requires-Dist: requests
